rero_invenio_files/__init__.py
rero_invenio_files/config.py
rero_invenio_files/ext.py
rero_invenio_files/pdf/.DS_Store
rero_invenio_files/pdf/__init__.py
rero_invenio_files/pdf/fonts/NotoSans-Bold.ttf
rero_invenio_files/pdf/fonts/NotoSans-BoldItalic.ttf
rero_invenio_files/pdf/fonts/NotoSans-Italic.ttf
rero_invenio_files/pdf/fonts/NotoSans-Regular.ttf
rero_invenio_files/pdf/fonts/OFL.txt
rero_invenio_files/pdf/graphs/bar_chart.jpeg
rero_invenio_files/pdf/graphs/line_chart.jpeg
rero_invenio_files/pdf/graphs/pie_chart.jpeg
rero_invenio_files/pdf/graphs/scatter_chart.jpeg
rero_invenio_files/pdf/logos/Logo_1.jpg
rero_invenio_files/pdf/logos/Logo_2.jpg
rero_invenio_files/pdf/logos/Logo_3.jpg
rero_invenio_files/pdf/logos/Logo_4.jpg
rero_invenio_files/records/__init__.py
rero_invenio_files/records/api.py
rero_invenio_files/records/components.py
rero_invenio_files/records/jsonschemas/__init__.py
rero_invenio_files/records/jsonschemas/records/record-v1.0.0.json
rero_invenio_files/records/mappings/__init__.py
rero_invenio_files/records/mappings/v7/__init__.py
rero_invenio_files/records/mappings/v7/records/record-v1.0.0.json
rero_invenio_files/records/models.py
rero_invenio_files/records/permissions.py
rero_invenio_files/records/previewer.py
rero_invenio_files/records/resources.py
rero_invenio_files/records/schema.py
rero_invenio_files/records/services.py
rero_invenio_files/views.py
rero_invenio_files-1.2.0.dist-info/licenses/LICENSE
rero_invenio_files-1.2.0.dist-info/WHEEL
rero_invenio_files-1.2.0.dist-info/entry_points.txt
rero_invenio_files-1.2.0.dist-info/METADATA
rero_invenio_files-1.2.0.dist-info/RECORD
