Metadata-Version: 2.4
Name: rero-invenio-files
Version: 1.2.0
Summary: Files support for the RERO invenio instances.
Author: RERO
Author-email: RERO <software@rero.ch>
License-Expression: AGPL-3.0
License-File: LICENSE
Requires-Dist: invenio-records-resources>=7.0.0
Requires-Dist: invenio-search[elasticsearch7]>=3.0.0,<4.0.0
Requires-Dist: invenio-db[postgresql]>=2.0.0,<3.0.0
Requires-Dist: fpdf2
Requires-Dist: pymupdf
Requires-Dist: invenio-previewer
Requires-Dist: invenio-theme
Requires-Dist: poethepoet>=0.36.0
Requires-Python: >=3.9.2, <3.13
